{
  "viêm phổi": 0,
  "sốt virus": 1,
  "ngộ độc thực phẩm": 2,
  "thiếu máu": 3,
  "cao huyết áp": 4,
  "covid-19": 5,
  "Vàng da": 6,
  "Cường giáp": 7,
  "Trĩ hỗn hợp (lòi dom)": 8,
  "Bệnh lao": 9,
  "Viêm gan do rượu": 10,
  "Đau tim": 11,
  "Gerd": 12,
  "Sốt xuất huyết": 13,
  "Liệt (Xuất huyết não)": 14,
  "Nhiễm trùng đường tiết niệu": 15,
  "chốc lở": 16,
  "Bệnh ứ mật mãn tính": 17,
  "Bệnh loét dạ dày tá tràng": 18,
  "Sốt rét": 19,
  "Viêm dạ dày ruột": 20,
  "Tĩnh mạch giãn": 21,
  "Viêm gan E": 22,
  "Viêm gan C": 23,
  "mụn trứng cá": 24,
  "Viêm gan D": 25,
  "Nhau cài răng lược": 26,
  "Dị ứng": 27,
  "(Chóng mặt) Chóng mặt tư thế Paroymsal": 28,
  "Bệnh xương khớp": 29,
  "Nhiễm trùng nấm": 30,
  "Bệnh vẩy nến": 31,
  "Phản ứng thuốc": 32,
  "Bệnh tiểu đường": 33,
  "Bệnh trào ngược dạ dày thực quản": 34,
  "Suy giáp": 35,
  "Viêm gan A": 36,
  "Hạ đường huyết": 37,
  "thương hàn": 38,
  "Viêm khớp": 39,
  "Viêm phổi": 40,
  "Bệnh thoái hóa đốt sống cổ": 41,
  "Hen phế quản": 42,
  "Đau nửa đầu": 43,
  "Tăng huyết áp": 44,
  "Viêm gan B": 45,
  "Cảm lạnh thông thường": 46,
  "Thủy đậu": 47,
  "AIDS": 48,
  "Gàu": 49,
  "Chấn thương ACL": 50,
  "Sự phát triển quá mức của vi khuẩn đường ruột nhỏ": 51,
  "Bệnh tiểu đường thai kỳ": 52,
  "Đầu gối sưng": 53,
  "Con mạt bụi": 54,
  "Rách sụn viền hông": 55,
  "Dị dạng động tĩnh mạch": 56,
  "Say máy bay": 57,
  "Nhiễm trùng thận": 58,
  "Viêm âm đạo do vi khuẩn": 59,
  "Ung thư biểu mô tiểu thùy tại chỗ": 60,
  "Đi bộ bằng ngón chân": 61,
  "Túi dưới mắt": 62,
  "Ung thư hậu môn": 63,
  "Ung thư biểu mô ống": 64,
  "Trào ngược axit ở trẻ sơ sinh": 65,
  "Ung thư tuyến tiền liệt giai đoạn 4": 66,
  "Ung thư xương": 67,
  "Xương sườn bị gãy": 68,
  "Vấn đề cân bằng": 69,
  "Lỗ thông bầu dục": 70,
  "Bệnh Raynaud": 71,
  "Hội chứng đau cơ": 72,
  "Tràn khí màng phổi": 73,
  "Sarcoma mô mềm": 74,
  "Tắc ruột": 75,
  "Ngón chân búa và ngón chân búa": 76,
  "Hạ natri máu": 77,
  "Mụn cóc thông thường": 78,
  "Bệnh truyền nhiễm": 79,
  "Gan to": 80,
  "Móng chân mọc ngược": 81,
  "Hội chứng Dressler": 82,
  "Tăng sản không điển hình": 83,
  "Bóc tách động mạch vành tự phát": 84,
  "Gãy mắt cá chân": 85
}